{
    "size": {
        "fontLineHeight": {
            "--gy-font-line-height-100": {
                "dls": "--gy",
                "branch": null,
                "value": "100%",
                "dynamicType": null,
                "spread": null,
                "offsetX": null,
                "offsetY": null,
                "blur": null,
                "fontFamily": null,
                "fontSize": null,
                "fontLineHeight": null,
                "fontWeight": null,
                "linkedSpaceToken": null,
                "linkedBorderRadiusToken": null,
                "linkedBorderWidthToken": null,
                "linkedOpacityToken": null,
                "lightValue": null,
                "darkValue": null,
                "linkedColorCoreToken": null,
                "linkedColorAliasToken": null,
                "tokenName": "--gy-font-line-height-100",
                "deprecated": null
            },
            "--gy-font-line-height-200": {
                "dls": "--gy",
                "branch": null,
                "value": "115%",
                "dynamicType": null,
                "spread": null,
                "offsetX": null,
                "offsetY": null,
                "blur": null,
                "fontFamily": null,
                "fontSize": null,
                "fontLineHeight": null,
                "fontWeight": null,
                "linkedSpaceToken": null,
                "linkedBorderRadiusToken": null,
                "linkedBorderWidthToken": null,
                "linkedOpacityToken": null,
                "lightValue": null,
                "darkValue": null,
                "linkedColorCoreToken": null,
                "linkedColorAliasToken": null,
                "tokenName": "--gy-font-line-height-200",
                "deprecated": null
            },
            "--gy-font-line-height-300": {
                "dls": "--gy",
                "branch": null,
                "value": "125%",
                "dynamicType": null,
                "spread": null,
                "offsetX": null,
                "offsetY": null,
                "blur": null,
                "fontFamily": null,
                "fontSize": null,
                "fontLineHeight": null,
                "fontWeight": null,
                "linkedSpaceToken": null,
                "linkedBorderRadiusToken": null,
                "linkedBorderWidthToken": null,
                "linkedOpacityToken": null,
                "lightValue": null,
                "darkValue": null,
                "linkedColorCoreToken": null,
                "linkedColorAliasToken": null,
                "tokenName": "--gy-font-line-height-300",
                "deprecated": null
            },
            "--gy-font-line-height-400": {
                "dls": "--gy",
                "branch": null,
                "value": "135%",
                "dynamicType": null,
                "spread": null,
                "offsetX": null,
                "offsetY": null,
                "blur": null,
                "fontFamily": null,
                "fontSize": null,
                "fontLineHeight": null,
                "fontWeight": null,
                "linkedSpaceToken": null,
                "linkedBorderRadiusToken": null,
                "linkedBorderWidthToken": null,
                "linkedOpacityToken": null,
                "lightValue": null,
                "darkValue": null,
                "linkedColorCoreToken": null,
                "linkedColorAliasToken": null,
                "tokenName": "--gy-font-line-height-400",
                "deprecated": null
            },
            "--gy-font-line-height-500": {
                "dls": "--gy",
                "branch": null,
                "value": "150%",
                "dynamicType": null,
                "spread": null,
                "offsetX": null,
                "offsetY": null,
                "blur": null,
                "fontFamily": null,
                "fontSize": null,
                "fontLineHeight": null,
                "fontWeight": null,
                "linkedSpaceToken": null,
                "linkedBorderRadiusToken": null,
                "linkedBorderWidthToken": null,
                "linkedOpacityToken": null,
                "lightValue": null,
                "darkValue": null,
                "linkedColorCoreToken": null,
                "linkedColorAliasToken": null,
                "tokenName": "--gy-font-line-height-500",
                "deprecated": null
            }
        }
    }
}