{
    "font": {
        "core": {
            "--gy-native-font-style-paragraph-primary-default": {
                "dls": "--gy",
                "branch": "native",
                "family": "font",
                "type": {
                    "": "paragraph",
                    "dynamic": null
                },
                "modifier": "primary-default",
                "scale": null,
                "state": null,
                "component": null,
                "value": null,
                "dynamicType": null,
                "spread": null,
                "offsetX": null,
                "offsetY": null,
                "blur": null,
                "fontFamily": {
                    "mc": "{fontFamily.name.--gy-font-family-primary.value.mc}",
                    "hb": null
                },
                "fontSize": {
                    "mc": "{size.fontSize.--gy-native-font-size-body-1.value.mc}",
                    "hb": null
                },
                "fontLineHeight": {
                    "mc": "{size.fontLineHeight.--gy-font-line-height-300.value}",
                    "hb": null
                },
                "fontWeight": {
                    "mc": "{size.fontWeight.--gy-font-weight-regular.value}",
                    "hb": null
                },
                "linkedSpaceToken": null,
                "linkedBorderRadiusToken": null,
                "linkedBorderWidthToken": null,
                "linkedOpacityToken": null,
                "lightValue": null,
                "darkValue": null,
                "linkedColorCoreToken": null,
                "linkedColorAliasToken": {
                    "mc": "{color.aliases.--gy-native-common-color-text-body-paragraph-primary-default.linkedColorCoreToken.mc}",
                    "hb": null
                },
                "tokenName": "--gy-native-font-style-paragraph-primary-default",
                "deprecated": null
            },
            "--gy-native-font-style-paragraph-primary-reverse": {
                "dls": "--gy",
                "branch": "native",
                "family": "font",
                "type": {
                    "": "paragraph",
                    "dynamic": null
                },
                "modifier": "primary-reverse",
                "scale": null,
                "state": null,
                "component": null,
                "value": null,
                "dynamicType": null,
                "spread": null,
                "offsetX": null,
                "offsetY": null,
                "blur": null,
                "fontFamily": {
                    "mc": "{fontFamily.name.--gy-font-family-primary.value.mc}",
                    "hb": null
                },
                "fontSize": {
                    "mc": "{size.fontSize.--gy-native-font-size-body-1.value.mc}",
                    "hb": null
                },
                "fontLineHeight": {
                    "mc": "{size.fontLineHeight.--gy-font-line-height-300.value}",
                    "hb": null
                },
                "fontWeight": {
                    "mc": "{size.fontWeight.--gy-font-weight-regular.value}",
                    "hb": null
                },
                "linkedSpaceToken": null,
                "linkedBorderRadiusToken": null,
                "linkedBorderWidthToken": null,
                "linkedOpacityToken": null,
                "lightValue": null,
                "darkValue": null,
                "linkedColorCoreToken": null,
                "linkedColorAliasToken": {
                    "mc": "{color.aliases.--gy-native-common-color-text-body-paragraph-primary-reverse.linkedColorCoreToken.mc}",
                    "hb": null
                },
                "tokenName": "--gy-native-font-style-paragraph-primary-reverse",
                "deprecated": null
            },
            "--gy-native-font-style-paragraph-secondary-default": {
                "dls": "--gy",
                "branch": "native",
                "family": "font",
                "type": {
                    "": "paragraph",
                    "dynamic": null
                },
                "modifier": "secondary-default",
                "scale": null,
                "state": null,
                "component": null,
                "value": null,
                "dynamicType": null,
                "spread": null,
                "offsetX": null,
                "offsetY": null,
                "blur": null,
                "fontFamily": {
                    "mc": "{fontFamily.name.--gy-font-family-primary.value.mc}",
                    "hb": null
                },
                "fontSize": {
                    "mc": "{size.fontSize.--gy-native-font-size-body-2.value.mc}",
                    "hb": null
                },
                "fontLineHeight": {
                    "mc": "{size.fontLineHeight.--gy-font-line-height-300.value}",
                    "hb": null
                },
                "fontWeight": {
                    "mc": "{size.fontWeight.--gy-font-weight-regular.value}",
                    "hb": null
                },
                "linkedSpaceToken": null,
                "linkedBorderRadiusToken": null,
                "linkedBorderWidthToken": null,
                "linkedOpacityToken": null,
                "lightValue": null,
                "darkValue": null,
                "linkedColorCoreToken": null,
                "linkedColorAliasToken": {
                    "mc": "{color.aliases.--gy-native-common-color-text-body-paragraph-secondary-default.linkedColorCoreToken.mc}",
                    "hb": null
                },
                "tokenName": "--gy-native-font-style-paragraph-secondary-default",
                "deprecated": null
            },
            "--gy-native-font-style-paragraph-secondary-subdued": {
                "dls": "--gy",
                "branch": "native",
                "family": "font",
                "type": {
                    "": "paragraph",
                    "dynamic": null
                },
                "modifier": "secondary-subdued",
                "scale": null,
                "state": null,
                "component": null,
                "value": null,
                "dynamicType": null,
                "spread": null,
                "offsetX": null,
                "offsetY": null,
                "blur": null,
                "fontFamily": {
                    "mc": "{fontFamily.name.--gy-font-family-primary.value.mc}",
                    "hb": null
                },
                "fontSize": {
                    "mc": "{size.fontSize.--gy-native-font-size-body-2.value.mc}",
                    "hb": null
                },
                "fontLineHeight": {
                    "mc": "{size.fontLineHeight.--gy-font-line-height-300.value}",
                    "hb": null
                },
                "fontWeight": {
                    "mc": "{size.fontWeight.--gy-font-weight-regular.value}",
                    "hb": null
                },
                "linkedSpaceToken": null,
                "linkedBorderRadiusToken": null,
                "linkedBorderWidthToken": null,
                "linkedOpacityToken": null,
                "lightValue": null,
                "darkValue": null,
                "linkedColorCoreToken": null,
                "linkedColorAliasToken": {
                    "mc": "{color.aliases.--gy-native-common-color-text-body-paragraph-secondary-subdued.linkedColorCoreToken.mc}",
                    "hb": null
                },
                "tokenName": "--gy-native-font-style-paragraph-secondary-subdued",
                "deprecated": null
            },
            "--gy-native-font-style-paragraph-secondary-reverse": {
                "dls": "--gy",
                "branch": "native",
                "family": "font",
                "type": {
                    "": "paragraph",
                    "dynamic": null
                },
                "modifier": "secondary-reverse",
                "scale": null,
                "state": null,
                "component": null,
                "value": null,
                "dynamicType": null,
                "spread": null,
                "offsetX": null,
                "offsetY": null,
                "blur": null,
                "fontFamily": {
                    "mc": "{fontFamily.name.--gy-font-family-primary.value.mc}",
                    "hb": null
                },
                "fontSize": {
                    "mc": "{size.fontSize.--gy-native-font-size-body-2.value.mc}",
                    "hb": null
                },
                "fontLineHeight": {
                    "mc": "{size.fontLineHeight.--gy-font-line-height-300.value}",
                    "hb": null
                },
                "fontWeight": {
                    "mc": "{size.fontWeight.--gy-font-weight-regular.value}",
                    "hb": null
                },
                "linkedSpaceToken": null,
                "linkedBorderRadiusToken": null,
                "linkedBorderWidthToken": null,
                "linkedOpacityToken": null,
                "lightValue": null,
                "darkValue": null,
                "linkedColorCoreToken": null,
                "linkedColorAliasToken": {
                    "mc": "{color.aliases.--gy-native-common-color-text-body-paragraph-secondary-reverse.linkedColorCoreToken.mc}",
                    "hb": null
                },
                "tokenName": "--gy-native-font-style-paragraph-secondary-reverse",
                "deprecated": null
            },
            "--gy-native-font-style-callout-primary-default": {
                "dls": "--gy",
                "branch": "native",
                "family": "font",
                "type": {
                    "": "callout",
                    "dynamic": null
                },
                "modifier": "primary-default",
                "scale": null,
                "state": null,
                "component": null,
                "value": null,
                "dynamicType": null,
                "spread": null,
                "offsetX": null,
                "offsetY": null,
                "blur": null,
                "fontFamily": {
                    "mc": "{fontFamily.name.--gy-font-family-primary.value.mc}",
                    "hb": null
                },
                "fontSize": {
                    "mc": "{size.fontSize.--gy-native-font-size-heading-4.value.mc}",
                    "hb": null
                },
                "fontLineHeight": {
                    "mc": "{size.fontLineHeight.--gy-font-line-height-300.value}",
                    "hb": null
                },
                "fontWeight": {
                    "mc": "{size.fontWeight.--gy-font-weight-bold.value}",
                    "hb": null
                },
                "linkedSpaceToken": null,
                "linkedBorderRadiusToken": null,
                "linkedBorderWidthToken": null,
                "linkedOpacityToken": null,
                "lightValue": null,
                "darkValue": null,
                "linkedColorCoreToken": null,
                "linkedColorAliasToken": {
                    "mc": "{color.aliases.--gy-native-common-color-text-body-callout-primary-default.linkedColorCoreToken.mc}",
                    "hb": null
                },
                "tokenName": "--gy-native-font-style-callout-primary-default",
                "deprecated": null
            },
            "--gy-native-font-style-callout-primary-reverse": {
                "dls": "--gy",
                "branch": "native",
                "family": "font",
                "type": {
                    "": "callout",
                    "dynamic": null
                },
                "modifier": "primary-reverse",
                "scale": null,
                "state": null,
                "component": null,
                "value": null,
                "dynamicType": null,
                "spread": null,
                "offsetX": null,
                "offsetY": null,
                "blur": null,
                "fontFamily": {
                    "mc": "{fontFamily.name.--gy-font-family-primary.value.mc}",
                    "hb": null
                },
                "fontSize": {
                    "mc": "{size.fontSize.--gy-native-font-size-heading-4.value.mc}",
                    "hb": null
                },
                "fontLineHeight": {
                    "mc": "{size.fontLineHeight.--gy-font-line-height-300.value}",
                    "hb": null
                },
                "fontWeight": {
                    "mc": "{size.fontWeight.--gy-font-weight-bold.value}",
                    "hb": null
                },
                "linkedSpaceToken": null,
                "linkedBorderRadiusToken": null,
                "linkedBorderWidthToken": null,
                "linkedOpacityToken": null,
                "lightValue": null,
                "darkValue": null,
                "linkedColorCoreToken": null,
                "linkedColorAliasToken": {
                    "mc": "{color.aliases.--gy-native-common-color-text-body-callout-primary-reverse.linkedColorCoreToken.mc}",
                    "hb": null
                },
                "tokenName": "--gy-native-font-style-callout-primary-reverse",
                "deprecated": null
            },
            "--gy-native-font-style-callout-primary-error": {
                "dls": "--gy",
                "branch": "native",
                "family": "font",
                "type": {
                    "": "callout",
                    "dynamic": null
                },
                "modifier": "primary-error",
                "scale": null,
                "state": null,
                "component": null,
                "value": null,
                "dynamicType": null,
                "spread": null,
                "offsetX": null,
                "offsetY": null,
                "blur": null,
                "fontFamily": {
                    "mc": "{fontFamily.name.--gy-font-family-primary.value.mc}",
                    "hb": null
                },
                "fontSize": {
                    "mc": "{size.fontSize.--gy-native-font-size-heading-4.value.mc}",
                    "hb": null
                },
                "fontLineHeight": {
                    "mc": "{size.fontLineHeight.--gy-font-line-height-300.value}",
                    "hb": null
                },
                "fontWeight": {
                    "mc": "{size.fontWeight.--gy-font-weight-bold.value}",
                    "hb": null
                },
                "linkedSpaceToken": null,
                "linkedBorderRadiusToken": null,
                "linkedBorderWidthToken": null,
                "linkedOpacityToken": null,
                "lightValue": null,
                "darkValue": null,
                "linkedColorCoreToken": null,
                "linkedColorAliasToken": {
                    "mc": "{color.aliases.--gy-native-common-color-text-body-callout-primary-error.linkedColorCoreToken.mc}",
                    "hb": null
                },
                "tokenName": "--gy-native-font-style-callout-primary-error",
                "deprecated": null
            },
            "--gy-native-font-style-callout-primary-warning": {
                "dls": "--gy",
                "branch": "native",
                "family": "font",
                "type": {
                    "": "callout",
                    "dynamic": null
                },
                "modifier": "primary-warning",
                "scale": null,
                "state": null,
                "component": null,
                "value": null,
                "dynamicType": null,
                "spread": null,
                "offsetX": null,
                "offsetY": null,
                "blur": null,
                "fontFamily": {
                    "mc": "{fontFamily.name.--gy-font-family-primary.value.mc}",
                    "hb": null
                },
                "fontSize": {
                    "mc": "{size.fontSize.--gy-native-font-size-heading-4.value.mc}",
                    "hb": null
                },
                "fontLineHeight": {
                    "mc": "{size.fontLineHeight.--gy-font-line-height-300.value}",
                    "hb": null
                },
                "fontWeight": {
                    "mc": "{size.fontWeight.--gy-font-weight-bold.value}",
                    "hb": null
                },
                "linkedSpaceToken": null,
                "linkedBorderRadiusToken": null,
                "linkedBorderWidthToken": null,
                "linkedOpacityToken": null,
                "lightValue": null,
                "darkValue": null,
                "linkedColorCoreToken": null,
                "linkedColorAliasToken": {
                    "mc": "{color.aliases.--gy-native-common-color-text-body-callout-primary-warning.linkedColorCoreToken.mc}",
                    "hb": null
                },
                "tokenName": "--gy-native-font-style-callout-primary-warning",
                "deprecated": null
            },
            "--gy-native-font-style-callout-primary-success": {
                "dls": "--gy",
                "branch": "native",
                "family": "font",
                "type": {
                    "": "callout",
                    "dynamic": null
                },
                "modifier": "primary-success",
                "scale": null,
                "state": null,
                "component": null,
                "value": null,
                "dynamicType": null,
                "spread": null,
                "offsetX": null,
                "offsetY": null,
                "blur": null,
                "fontFamily": {
                    "mc": "{fontFamily.name.--gy-font-family-primary.value.mc}",
                    "hb": null
                },
                "fontSize": {
                    "mc": "{size.fontSize.--gy-native-font-size-heading-4.value.mc}",
                    "hb": null
                },
                "fontLineHeight": {
                    "mc": "{size.fontLineHeight.--gy-font-line-height-300.value}",
                    "hb": null
                },
                "fontWeight": {
                    "mc": "{size.fontWeight.--gy-font-weight-bold.value}",
                    "hb": null
                },
                "linkedSpaceToken": null,
                "linkedBorderRadiusToken": null,
                "linkedBorderWidthToken": null,
                "linkedOpacityToken": null,
                "lightValue": null,
                "darkValue": null,
                "linkedColorCoreToken": null,
                "linkedColorAliasToken": {
                    "mc": "{color.aliases.--gy-native-common-color-text-body-callout-primary-success.linkedColorCoreToken.mc}",
                    "hb": null
                },
                "tokenName": "--gy-native-font-style-callout-primary-success",
                "deprecated": null
            },
            "--gy-native-font-style-callout-secondary-default": {
                "dls": "--gy",
                "branch": "native",
                "family": "font",
                "type": {
                    "": "callout",
                    "dynamic": null
                },
                "modifier": "secondary-default",
                "scale": null,
                "state": null,
                "component": null,
                "value": null,
                "dynamicType": null,
                "spread": null,
                "offsetX": null,
                "offsetY": null,
                "blur": null,
                "fontFamily": {
                    "mc": "{fontFamily.name.--gy-font-family-primary.value.mc}",
                    "hb": null
                },
                "fontSize": {
                    "mc": "{size.fontSize.--gy-native-font-size-body-1.value.mc}",
                    "hb": null
                },
                "fontLineHeight": {
                    "mc": "{size.fontLineHeight.--gy-font-line-height-300.value}",
                    "hb": null
                },
                "fontWeight": {
                    "mc": "{size.fontWeight.--gy-font-weight-bold.value}",
                    "hb": null
                },
                "linkedSpaceToken": null,
                "linkedBorderRadiusToken": null,
                "linkedBorderWidthToken": null,
                "linkedOpacityToken": null,
                "lightValue": null,
                "darkValue": null,
                "linkedColorCoreToken": null,
                "linkedColorAliasToken": {
                    "mc": "{color.aliases.--gy-native-common-color-text-body-callout-secondary-default.linkedColorCoreToken.mc}",
                    "hb": null
                },
                "tokenName": "--gy-native-font-style-callout-secondary-default",
                "deprecated": null
            },
            "--gy-native-font-style-callout-secondary-reverse": {
                "dls": "--gy",
                "branch": "native",
                "family": "font",
                "type": {
                    "": "callout",
                    "dynamic": null
                },
                "modifier": "secondary-reverse",
                "scale": null,
                "state": null,
                "component": null,
                "value": null,
                "dynamicType": null,
                "spread": null,
                "offsetX": null,
                "offsetY": null,
                "blur": null,
                "fontFamily": {
                    "mc": "{fontFamily.name.--gy-font-family-primary.value.mc}",
                    "hb": null
                },
                "fontSize": {
                    "mc": "{size.fontSize.--gy-native-font-size-body-1.value.mc}",
                    "hb": null
                },
                "fontLineHeight": {
                    "mc": "{size.fontLineHeight.--gy-font-line-height-300.value}",
                    "hb": null
                },
                "fontWeight": {
                    "mc": "{size.fontWeight.--gy-font-weight-bold.value}",
                    "hb": null
                },
                "linkedSpaceToken": null,
                "linkedBorderRadiusToken": null,
                "linkedBorderWidthToken": null,
                "linkedOpacityToken": null,
                "lightValue": null,
                "darkValue": null,
                "linkedColorCoreToken": null,
                "linkedColorAliasToken": {
                    "mc": "{color.aliases.--gy-native-common-color-text-body-callout-secondary-reverse.linkedColorCoreToken.mc}",
                    "hb": null
                },
                "tokenName": "--gy-native-font-style-callout-secondary-reverse",
                "deprecated": null
            },
            "--gy-native-font-style-callout-secondary-error": {
                "dls": "--gy",
                "branch": "native",
                "family": "font",
                "type": {
                    "": "callout",
                    "dynamic": null
                },
                "modifier": "secondary-error",
                "scale": null,
                "state": null,
                "component": null,
                "value": null,
                "dynamicType": null,
                "spread": null,
                "offsetX": null,
                "offsetY": null,
                "blur": null,
                "fontFamily": {
                    "mc": "{fontFamily.name.--gy-font-family-primary.value.mc}",
                    "hb": null
                },
                "fontSize": {
                    "mc": "{size.fontSize.--gy-native-font-size-body-1.value.mc}",
                    "hb": null
                },
                "fontLineHeight": {
                    "mc": "{size.fontLineHeight.--gy-font-line-height-300.value}",
                    "hb": null
                },
                "fontWeight": {
                    "mc": "{size.fontWeight.--gy-font-weight-bold.value}",
                    "hb": null
                },
                "linkedSpaceToken": null,
                "linkedBorderRadiusToken": null,
                "linkedBorderWidthToken": null,
                "linkedOpacityToken": null,
                "lightValue": null,
                "darkValue": null,
                "linkedColorCoreToken": null,
                "linkedColorAliasToken": {
                    "mc": "{color.aliases.--gy-native-common-color-text-body-callout-secondary-error.linkedColorCoreToken.mc}",
                    "hb": null
                },
                "tokenName": "--gy-native-font-style-callout-secondary-error",
                "deprecated": null
            },
            "--gy-native-font-style-callout-secondary-warning": {
                "dls": "--gy",
                "branch": "native",
                "family": "font",
                "type": {
                    "": "callout",
                    "dynamic": null
                },
                "modifier": "secondary-warning",
                "scale": null,
                "state": null,
                "component": null,
                "value": null,
                "dynamicType": null,
                "spread": null,
                "offsetX": null,
                "offsetY": null,
                "blur": null,
                "fontFamily": {
                    "mc": "{fontFamily.name.--gy-font-family-primary.value.mc}",
                    "hb": null
                },
                "fontSize": {
                    "mc": "{size.fontSize.--gy-native-font-size-body-1.value.mc}",
                    "hb": null
                },
                "fontLineHeight": {
                    "mc": "{size.fontLineHeight.--gy-font-line-height-300.value}",
                    "hb": null
                },
                "fontWeight": {
                    "mc": "{size.fontWeight.--gy-font-weight-bold.value}",
                    "hb": null
                },
                "linkedSpaceToken": null,
                "linkedBorderRadiusToken": null,
                "linkedBorderWidthToken": null,
                "linkedOpacityToken": null,
                "lightValue": null,
                "darkValue": null,
                "linkedColorCoreToken": null,
                "linkedColorAliasToken": {
                    "mc": "{color.aliases.--gy-native-common-color-text-body-callout-secondary-warning.linkedColorCoreToken.mc}",
                    "hb": null
                },
                "tokenName": "--gy-native-font-style-callout-secondary-warning",
                "deprecated": null
            },
            "--gy-native-font-style-callout-secondary-success": {
                "dls": "--gy",
                "branch": "native",
                "family": "font",
                "type": {
                    "": "callout",
                    "dynamic": null
                },
                "modifier": "secondary-success",
                "scale": null,
                "state": null,
                "component": null,
                "value": null,
                "dynamicType": null,
                "spread": null,
                "offsetX": null,
                "offsetY": null,
                "blur": null,
                "fontFamily": {
                    "mc": "{fontFamily.name.--gy-font-family-primary.value.mc}",
                    "hb": null
                },
                "fontSize": {
                    "mc": "{size.fontSize.--gy-native-font-size-body-1.value.mc}",
                    "hb": null
                },
                "fontLineHeight": {
                    "mc": "{size.fontLineHeight.--gy-font-line-height-300.value}",
                    "hb": null
                },
                "fontWeight": {
                    "mc": "{size.fontWeight.--gy-font-weight-bold.value}",
                    "hb": null
                },
                "linkedSpaceToken": null,
                "linkedBorderRadiusToken": null,
                "linkedBorderWidthToken": null,
                "linkedOpacityToken": null,
                "lightValue": null,
                "darkValue": null,
                "linkedColorCoreToken": null,
                "linkedColorAliasToken": {
                    "mc": "{color.aliases.--gy-native-common-color-text-body-callout-secondary-success.linkedColorCoreToken.mc}",
                    "hb": null
                },
                "tokenName": "--gy-native-font-style-callout-secondary-success",
                "deprecated": null
            },
            "--gy-native-font-style-callout-highlighted-s-default": {
                "dls": "--gy",
                "branch": "native",
                "family": "font",
                "type": {
                    "": "callout",
                    "dynamic": null
                },
                "modifier": "highlighted-s-default",
                "scale": null,
                "state": null,
                "component": null,
                "value": null,
                "dynamicType": null,
                "spread": null,
                "offsetX": null,
                "offsetY": null,
                "blur": null,
                "fontFamily": {
                    "mc": "{fontFamily.name.--gy-font-family-primary.value.mc}",
                    "hb": null
                },
                "fontSize": {
                    "mc": "{size.fontSize.--gy-native-font-size-heading-3.value.mc}",
                    "hb": null
                },
                "fontLineHeight": {
                    "mc": "{size.fontLineHeight.--gy-font-line-height-300.value}",
                    "hb": null
                },
                "fontWeight": {
                    "mc": "{size.fontWeight.--gy-font-weight-bold.value}",
                    "hb": null
                },
                "linkedSpaceToken": null,
                "linkedBorderRadiusToken": null,
                "linkedBorderWidthToken": null,
                "linkedOpacityToken": null,
                "lightValue": null,
                "darkValue": null,
                "linkedColorCoreToken": null,
                "linkedColorAliasToken": {
                    "mc": "{color.aliases.--gy-native-common-color-text-body-callout-highlighted-s-default.linkedColorCoreToken.mc}",
                    "hb": null
                },
                "tokenName": "--gy-native-font-style-callout-highlighted-s-default",
                "deprecated": null
            },
            "--gy-native-font-style-callout-highlighted-s-brand": {
                "dls": "--gy",
                "branch": "native",
                "family": "font",
                "type": {
                    "": "callout",
                    "dynamic": null
                },
                "modifier": "highlighted-s-brand",
                "scale": null,
                "state": null,
                "component": null,
                "value": null,
                "dynamicType": null,
                "spread": null,
                "offsetX": null,
                "offsetY": null,
                "blur": null,
                "fontFamily": {
                    "mc": "{fontFamily.name.--gy-font-family-primary.value.mc}",
                    "hb": null
                },
                "fontSize": {
                    "mc": "{size.fontSize.--gy-native-font-size-heading-3.value.mc}",
                    "hb": null
                },
                "fontLineHeight": {
                    "mc": "{size.fontLineHeight.--gy-font-line-height-300.value}",
                    "hb": null
                },
                "fontWeight": {
                    "mc": "{size.fontWeight.--gy-font-weight-bold.value}",
                    "hb": null
                },
                "linkedSpaceToken": null,
                "linkedBorderRadiusToken": null,
                "linkedBorderWidthToken": null,
                "linkedOpacityToken": null,
                "lightValue": null,
                "darkValue": null,
                "linkedColorCoreToken": null,
                "linkedColorAliasToken": {
                    "mc": "{color.aliases.--gy-native-common-color-text-body-callout-highlighted-s-brand.linkedColorCoreToken.mc}",
                    "hb": null
                },
                "tokenName": "--gy-native-font-style-callout-highlighted-s-brand",
                "deprecated": null
            },
            "--gy-native-font-style-callout-highlighted-s-reverse": {
                "dls": "--gy",
                "branch": "native",
                "family": "font",
                "type": {
                    "": "callout",
                    "dynamic": null
                },
                "modifier": "highlighted-s-reverse",
                "scale": null,
                "state": null,
                "component": null,
                "value": null,
                "dynamicType": null,
                "spread": null,
                "offsetX": null,
                "offsetY": null,
                "blur": null,
                "fontFamily": {
                    "mc": "{fontFamily.name.--gy-font-family-primary.value.mc}",
                    "hb": null
                },
                "fontSize": {
                    "mc": "{size.fontSize.--gy-native-font-size-heading-3.value.mc}",
                    "hb": null
                },
                "fontLineHeight": {
                    "mc": "{size.fontLineHeight.--gy-font-line-height-300.value}",
                    "hb": null
                },
                "fontWeight": {
                    "mc": "{size.fontWeight.--gy-font-weight-bold.value}",
                    "hb": null
                },
                "linkedSpaceToken": null,
                "linkedBorderRadiusToken": null,
                "linkedBorderWidthToken": null,
                "linkedOpacityToken": null,
                "lightValue": null,
                "darkValue": null,
                "linkedColorCoreToken": null,
                "linkedColorAliasToken": {
                    "mc": "{color.aliases.--gy-native-common-color-text-body-callout-highlighted-s-reverse.linkedColorCoreToken.mc}",
                    "hb": null
                },
                "tokenName": "--gy-native-font-style-callout-highlighted-s-reverse",
                "deprecated": null
            },
            "--gy-native-font-style-caption-default": {
                "dls": "--gy",
                "branch": "native",
                "family": "font",
                "type": {
                    "": "caption",
                    "dynamic": null
                },
                "modifier": "default",
                "scale": null,
                "state": null,
                "component": null,
                "value": null,
                "dynamicType": null,
                "spread": null,
                "offsetX": null,
                "offsetY": null,
                "blur": null,
                "fontFamily": {
                    "mc": "{fontFamily.name.--gy-font-family-primary.value.mc}",
                    "hb": null
                },
                "fontSize": {
                    "mc": "{size.fontSize.--gy-native-font-size-body-3.value.mc}",
                    "hb": null
                },
                "fontLineHeight": {
                    "mc": "{size.fontLineHeight.--gy-font-line-height-300.value}",
                    "hb": null
                },
                "fontWeight": {
                    "mc": "{size.fontWeight.--gy-font-weight-regular.value}",
                    "hb": null
                },
                "linkedSpaceToken": null,
                "linkedBorderRadiusToken": null,
                "linkedBorderWidthToken": null,
                "linkedOpacityToken": null,
                "lightValue": null,
                "darkValue": null,
                "linkedColorCoreToken": null,
                "linkedColorAliasToken": {
                    "mc": "{color.aliases.--gy-native-common-color-text-body-caption-default.linkedColorCoreToken.mc}",
                    "hb": null
                },
                "tokenName": "--gy-native-font-style-caption-default",
                "deprecated": null
            },
            "--gy-native-font-style-caption-subdued": {
                "dls": "--gy",
                "branch": "native",
                "family": "font",
                "type": {
                    "": "caption",
                    "dynamic": null
                },
                "modifier": "subdued",
                "scale": null,
                "state": null,
                "component": null,
                "value": null,
                "dynamicType": null,
                "spread": null,
                "offsetX": null,
                "offsetY": null,
                "blur": null,
                "fontFamily": {
                    "mc": "{fontFamily.name.--gy-font-family-primary.value.mc}",
                    "hb": null
                },
                "fontSize": {
                    "mc": "{size.fontSize.--gy-native-font-size-body-3.value.mc}",
                    "hb": null
                },
                "fontLineHeight": {
                    "mc": "{size.fontLineHeight.--gy-font-line-height-300.value}",
                    "hb": null
                },
                "fontWeight": {
                    "mc": "{size.fontWeight.--gy-font-weight-regular.value}",
                    "hb": null
                },
                "linkedSpaceToken": null,
                "linkedBorderRadiusToken": null,
                "linkedBorderWidthToken": null,
                "linkedOpacityToken": null,
                "lightValue": null,
                "darkValue": null,
                "linkedColorCoreToken": null,
                "linkedColorAliasToken": {
                    "mc": "{color.aliases.--gy-native-common-color-text-body-caption-subdued.linkedColorCoreToken.mc}",
                    "hb": null
                },
                "tokenName": "--gy-native-font-style-caption-subdued",
                "deprecated": null
            },
            "--gy-native-font-style-caption-reverse": {
                "dls": "--gy",
                "branch": "native",
                "family": "font",
                "type": {
                    "": "caption",
                    "dynamic": null
                },
                "modifier": "reverse",
                "scale": null,
                "state": null,
                "component": null,
                "value": null,
                "dynamicType": null,
                "spread": null,
                "offsetX": null,
                "offsetY": null,
                "blur": null,
                "fontFamily": {
                    "mc": "{fontFamily.name.--gy-font-family-primary.value.mc}",
                    "hb": null
                },
                "fontSize": {
                    "mc": "{size.fontSize.--gy-native-font-size-body-3.value.mc}",
                    "hb": null
                },
                "fontLineHeight": {
                    "mc": "{size.fontLineHeight.--gy-font-line-height-300.value}",
                    "hb": null
                },
                "fontWeight": {
                    "mc": "{size.fontWeight.--gy-font-weight-regular.value}",
                    "hb": null
                },
                "linkedSpaceToken": null,
                "linkedBorderRadiusToken": null,
                "linkedBorderWidthToken": null,
                "linkedOpacityToken": null,
                "lightValue": null,
                "darkValue": null,
                "linkedColorCoreToken": null,
                "linkedColorAliasToken": {
                    "mc": "{color.aliases.--gy-native-common-color-text-body-caption-reverse.linkedColorCoreToken.mc}",
                    "hb": null
                },
                "tokenName": "--gy-native-font-style-caption-reverse",
                "deprecated": null
            },
            "--gy-native-font-style-caption-brand": {
                "dls": "--gy",
                "branch": "native",
                "family": "font",
                "type": {
                    "": "caption",
                    "dynamic": null
                },
                "modifier": "brand",
                "scale": null,
                "state": null,
                "component": null,
                "value": null,
                "dynamicType": null,
                "spread": null,
                "offsetX": null,
                "offsetY": null,
                "blur": null,
                "fontFamily": {
                    "mc": "{fontFamily.name.--gy-font-family-primary.value.mc}",
                    "hb": null
                },
                "fontSize": {
                    "mc": "{size.fontSize.--gy-native-font-size-body-3.value.mc}",
                    "hb": null
                },
                "fontLineHeight": {
                    "mc": "{size.fontLineHeight.--gy-font-line-height-400.value}",
                    "hb": null
                },
                "fontWeight": {
                    "mc": "{size.fontWeight.--gy-font-weight-semi-bold.value}",
                    "hb": null
                },
                "linkedSpaceToken": null,
                "linkedBorderRadiusToken": null,
                "linkedBorderWidthToken": null,
                "linkedOpacityToken": null,
                "lightValue": null,
                "darkValue": null,
                "linkedColorCoreToken": null,
                "linkedColorAliasToken": {
                    "mc": "{color.aliases.--gy-native-common-color-text-body-caption-brand.linkedColorCoreToken.mc}",
                    "hb": null
                },
                "tokenName": "--gy-native-font-style-caption-brand",
                "deprecated": null
            }
        }
    }
}